{"modified_time":[1783977679,23429377],"values":{"a1d28e862cf64a9f56197912b4405ac2":{"atoms":["O","H"],"bod_rmax":3.0,"compression":false,"crystal_name":"141_H2O_0","gsd":"141_H2O_0_nvt_final_pf0p6_0.gsd","inputfile":"../../inputs/141_H2O_0/","logsteps":100,"rdf_rmax":3.0,"replicas":4,"runtime":100000},"6054ad73f0682592891307a00e3d7a0d":{"atoms":["O","H"],"bod_rmax":3.0,"compression":true,"crystal_name":"141_H2O_0","gsd":"141_H2O_0_nvt_final_pf0p6_0.gsd","inputfile":"../../inputs/141_H2O_0/","logsteps":100,"rdf_rmax":3.0,"replicas":4,"runtime":100000}}}